{
  "armorSetName": "diamond",
  "performanceMode": true,
  "head": {
    "itemKey": "minecraft:diamond_helmet",
    "mustBeEmpty": false
  },
  "chest": {
    "itemKey": "minecraft:diamond_chestplate",
    "mustBeEmpty": false
  },
  "legs": {
    "itemKey": "minecraft:diamond_leggings",
    "mustBeEmpty": false
  },
  "boots": {
    "itemKey": "minecraft:diamond_boots",
    "mustBeEmpty": false
  },
  "fullSetBonuses": [
    {
      "type": "effect",
      "name": "minecraft:absorption",
      "value": 0,
      "modifierUUID": "49ffa3c1-479b-896b-8d98-efb433ba12c0",
      "description": "resistance",
      "attributeOperation": 0,
      "interactionType": "self",
      "interactionDuration": 600,
      "hideBonusDescription": false,
      "onlyImmuneToNewEffects": false
    }
  ],
  "hideGeneratedTooltip": false
}